main.py
bilibili_image-0.1.3.dist-info/entry_points.txt
bilibili_image-0.1.3.dist-info/LICENSE
bilibili_image-0.1.3.dist-info/WHEEL
bilibili_image-0.1.3.dist-info/METADATA
bilibili_image-0.1.3.dist-info/RECORD
