Metadata-Version: 2.1
Name: bilibili-image
Version: 0.1.3
Summary: 命令行下载bilibili封面图片
Home-page: https://github.com/guaifish/bilibili-image.git
License: MIT
Author: guaifish
Author-email: guaifish@hotmail.com
Requires-Python: >=3.6,<4.0
Classifier: License :: OSI Approved :: MIT License
Classifier: Programming Language :: Python :: 3
Classifier: Programming Language :: Python :: 3.6
Classifier: Programming Language :: Python :: 3.7
Classifier: Programming Language :: Python :: 3.8
Requires-Dist: parsel (>=1.6.0,<2.0.0)
Requires-Dist: requests (>=2.23.0,<3.0.0)
Project-URL: Repository, https://github.com/guaifish/bilibili-image.git
